shsqlcheck.py
shsqlcheck/__init__.py
sunghan_dbcheck-1.0.0.4.dist-info/METADATA
sunghan_dbcheck-1.0.0.4.dist-info/WHEEL
sunghan_dbcheck-1.0.0.4.dist-info/top_level.txt
sunghan_dbcheck-1.0.0.4.dist-info/RECORD
