Metadata-Version: 2.1
Name: sunghan-dbcheck
Version: 1.0.0.4
Summary: Sunghan Database Check
Home-page: https://github.com/choids001/python
Author: SungHan
License: SH
Platform: UNKNOWN
Requires-Python: >=3
